microsocksproxy/LICENSE
microsocksproxy/README.MD
microsocksproxy/__init__.py
microsocksproxy/cygwin1.dll
microsocksproxy/microsocks.exe
microsocksproxy/requirements.txt
microsocksproxy/thirdparty.json
microsocksproxy-0.11.dist-info/LICENSE.rst
microsocksproxy-0.11.dist-info/METADATA
microsocksproxy-0.11.dist-info/WHEEL
microsocksproxy-0.11.dist-info/top_level.txt
microsocksproxy-0.11.dist-info/RECORD
