Metadata-Version: 2.1
Name: microsocksproxy
Version: 0.11
Summary: Wrapper for microsocks - multithreaded, small, efficient SOCKS5 server - Windows only
Home-page: https://github.com/hansalemaos/microsocksproxy
Author: Johannes Fischer
Author-email: <aulasparticularesdealemaosp@gmail.com>
License: MIT
Keywords: microsocks,socks5,windows,server
Classifier: Development Status :: 4 - Beta
Classifier: Programming Language :: Python :: 3 :: Only
Classifier: Programming Language :: Python :: 3.9
Classifier: Topic :: Scientific/Engineering :: Visualization
Classifier: Topic :: Software Development :: Libraries :: Python Modules
Classifier: Topic :: Text Editors :: Text Processing
Classifier: Topic :: Text Processing :: General
Classifier: Topic :: Text Processing :: Indexing
Classifier: Topic :: Text Processing :: Filters
Classifier: Topic :: Utilities
License-File: LICENSE.rst
Requires-Dist: ansi
Requires-Dist: kthread
Requires-Dist: kthread-sleep
Requires-Dist: psutil
